timesl/__init__.py
timesl/__version__.py
timesl/calendarx.py
timesl/clock.py
timesl/config.py
timesl/exceptions.py
timesl/units.py
timesl/core/sleep.py
timesl/core/state.py
timesl/core/vt.py
timesl-0.2.1.dist-info/licenses/LICENSE
timesl-0.2.1.dist-info/METADATA
timesl-0.2.1.dist-info/WHEEL
timesl-0.2.1.dist-info/top_level.txt
timesl-0.2.1.dist-info/RECORD
