Metadata-Version: 2.4
Name: timesl
Version: 0.2.1
Summary: The library includes advanced timekeeping and timing features, suitable for both very fast and very long time counting.
Author: Hoangdinhgg
License: MIT License
Project-URL: YouTube, https://youtube.com/@HOANGDINHGG
Classifier: Programming Language :: Python :: 3
Classifier: License :: OSI Approved :: MIT License
Classifier: Operating System :: OS Independent
Requires-Python: >=3.9
License-File: LICENSE
Dynamic: license-file
